llm_github_models.py
llm_github_models-0.17.1.dist-info/licenses/LICENSE
llm_github_models-0.17.1.dist-info/METADATA
llm_github_models-0.17.1.dist-info/WHEEL
llm_github_models-0.17.1.dist-info/entry_points.txt
llm_github_models-0.17.1.dist-info/top_level.txt
llm_github_models-0.17.1.dist-info/RECORD
