Metadata-Version: 2.4
Name: llm-github-models
Version: 0.17.1
Summary: LLM plugin to access GitHub Models API
Author: Anthony Shaw
License: Apache-2.0
Project-URL: Homepage, https://github.com/tonybaloney/llm-github-models
Project-URL: Changelog, https://github.com/tonybaloney/llm-github-models/releases
Project-URL: Issues, https://github.com/tonybaloney/llm-github-models/issues
Project-URL: CI, https://github.com/tonybaloney/llm-github-models/actions
Classifier: License :: OSI Approved :: Apache Software License
License-File: LICENSE
Requires-Dist: aiohttp>=3.11.18
Requires-Dist: llm>=0.26
Requires-Dist: azure-ai-inference>=1.0.0b8
Provides-Extra: test
Requires-Dist: pytest; extra == "test"
Requires-Dist: pytest-recording; extra == "test"
Requires-Dist: pytest-asyncio; extra == "test"
Requires-Dist: ruff; extra == "test"
Requires-Dist: pyright; extra == "test"
Dynamic: license-file
